aliyunsdkreid_cloud/__init__.py
aliyunsdkreid_cloud/endpoint.py
aliyunsdkreid_cloud/request/__init__.py
aliyunsdkreid_cloud/request/v20201029/DescribeBaseStatisticsRequest.py
aliyunsdkreid_cloud/request/v20201029/DescribeCameraStatisticsRequest.py
aliyunsdkreid_cloud/request/v20201029/DescribeCursorRequest.py
aliyunsdkreid_cloud/request/v20201029/DescribeCustomerFlowByLocationOfflineRequest.py
aliyunsdkreid_cloud/request/v20201029/DescribeCustomerFlowByLocationRequest.py
aliyunsdkreid_cloud/request/v20201029/DescribeDevicesRequest.py
aliyunsdkreid_cloud/request/v20201029/DescribeHeatMapRequest.py
aliyunsdkreid_cloud/request/v20201029/DescribeImageUrlsRequest.py
aliyunsdkreid_cloud/request/v20201029/DescribeIpcLiveAddressRequest.py
aliyunsdkreid_cloud/request/v20201029/DescribeOverviewDataRequest.py
aliyunsdkreid_cloud/request/v20201029/ImportSpecialPersonnelRequest.py
aliyunsdkreid_cloud/request/v20201029/ListActionDataRequest.py
aliyunsdkreid_cloud/request/v20201029/ListDevicesImagesRequest.py
aliyunsdkreid_cloud/request/v20201029/ListEmapRequest.py
aliyunsdkreid_cloud/request/v20201029/ListLocationRequest.py
aliyunsdkreid_cloud/request/v20201029/ListMaskDetectionResultsRequest.py
aliyunsdkreid_cloud/request/v20201029/ListPersonByImageRequest.py
aliyunsdkreid_cloud/request/v20201029/ListSpecialPersonnelByImageRequest.py
aliyunsdkreid_cloud/request/v20201029/ListStoreRequest.py
aliyunsdkreid_cloud/request/v20201029/PullActionDataRequest.py
aliyunsdkreid_cloud/request/v20201029/__init__.py
aliyun_python_sdk_reid_cloud-1.2.2.dist-info/LICENSE
aliyun_python_sdk_reid_cloud-1.2.2.dist-info/METADATA
aliyun_python_sdk_reid_cloud-1.2.2.dist-info/WHEEL
aliyun_python_sdk_reid_cloud-1.2.2.dist-info/top_level.txt
aliyun_python_sdk_reid_cloud-1.2.2.dist-info/RECORD
